bigcode_eval/__init__.py
bigcode_eval/arguments.py
bigcode_eval/base.py
bigcode_eval/evaluator.py
bigcode_eval/generation.py
bigcode_eval/main.py
bigcode_eval/main_non_hf.py
bigcode_eval/main_server.py
bigcode_eval/nemo_model.py
bigcode_eval/parsing_utils.py
bigcode_eval/trtllm_model.py
bigcode_eval/utils.py
bigcode_eval/llama_tokenizer/tokenizer.json
bigcode_eval/llama_tokenizer/tokenizer.model
bigcode_eval/llama_tokenizer/tokenizer_config.json
bigcode_eval/server/__init__.py
bigcode_eval/server/base_server.py
bigcode_eval/server/nim.py
bigcode_eval/server/nvcf.py
bigcode_eval/server/openai_messages_handlers.py
bigcode_eval/server/schemas.py
bigcode_eval/tasks/__init__.py
bigcode_eval/tasks/apps.py
bigcode_eval/tasks/bfcl.py
bigcode_eval/tasks/codexglue_code_to_text.py
bigcode_eval/tasks/codexglue_text_to_text.py
bigcode_eval/tasks/conala.py
bigcode_eval/tasks/concode.py
bigcode_eval/tasks/ds1000.py
bigcode_eval/tasks/gsm.py
bigcode_eval/tasks/humaneval.py
bigcode_eval/tasks/humanevalpack.py
bigcode_eval/tasks/humanevalpack_openai.py
bigcode_eval/tasks/humanevalplus.py
bigcode_eval/tasks/instruct_humaneval.py
bigcode_eval/tasks/instruct_wizard_humaneval.py
bigcode_eval/tasks/mbpp.py
bigcode_eval/tasks/mbppplus.py
bigcode_eval/tasks/mercury.py
bigcode_eval/tasks/multiple.py
bigcode_eval/tasks/parity.py
bigcode_eval/tasks/python_bugs.py
bigcode_eval/tasks/quixbugs.py
bigcode_eval/tasks/recode.py
bigcode_eval/tasks/santacoder_fim.py
bigcode_eval/tasks/spider.py
bigcode_eval/tasks/studenteval.py
bigcode_eval/tasks/verilog.py
bigcode_eval/tasks/custom_metrics/__init__.py
bigcode_eval/tasks/custom_metrics/beyond_eval.py
bigcode_eval/tasks/custom_metrics/code_eval.py
bigcode_eval/tasks/custom_metrics/codexglue_code_to_text_bleu.py
bigcode_eval/tasks/custom_metrics/diff_eval.py
bigcode_eval/tasks/custom_metrics/execute.py
bigcode_eval/tasks/custom_metrics/verilog_execute.py
bigcode_eval/tasks/custom_metrics/bfcl_metrics/__init__.py
nvidia_bigcode_eval-25.11.dist-info/licenses/LICENSE
nvidia_bigcode_eval-25.11.dist-info/METADATA
nvidia_bigcode_eval-25.11.dist-info/WHEEL
nvidia_bigcode_eval-25.11.dist-info/entry_points.txt
nvidia_bigcode_eval-25.11.dist-info/top_level.txt
nvidia_bigcode_eval-25.11.dist-info/RECORD
