Metadata-Version: 2.4
Name: nvidia_bigcode_eval
Version: 25.11
Summary: BigCode Evaluation Harness - packaged by NVIDIA
License: Apache 2.0
Classifier: Development Status :: 5 - Production/Stable
Classifier: Programming Language :: Python :: 3
Classifier: License :: OSI Approved :: Apache Software License
Classifier: Operating System :: OS Independent
Requires-Python: >=3.7
License-File: LICENSE
Requires-Dist: transformers>=4.25.1
Requires-Dist: datasets>=2.6.1
Requires-Dist: evaluate>=0.3.0
Requires-Dist: sacremoses>=0.1.0
Requires-Dist: huggingface_hub>=0.11.1
Requires-Dist: fsspec<2023.10.0
Requires-Dist: httpx>=0.27.0
Requires-Dist: nltk>=3.9.1
Requires-Dist: sqlparse==0.5.0
Requires-Dist: tree_sitter~=0.21.0
Requires-Dist: tree-sitter-java==0.21.0
Requires-Dist: tree-sitter-javascript==0.21.4
Requires-Dist: pydantic>=2.8.2
Requires-Dist: nemo-evaluator
Dynamic: classifier
Dynamic: description
Dynamic: description-content-type
Dynamic: license
Dynamic: license-file
Dynamic: requires-dist
Dynamic: requires-python
Dynamic: summary
